simple_plotter_qt/__init__.py
simple_plotter_qt/gui.py
simple_plotter_qt-0.1.0.dist-info/LICENSE
simple_plotter_qt-0.1.0.dist-info/METADATA
simple_plotter_qt-0.1.0.dist-info/NOTICE
simple_plotter_qt-0.1.0.dist-info/WHEEL
simple_plotter_qt-0.1.0.dist-info/entry_points.txt
simple_plotter_qt-0.1.0.dist-info/top_level.txt
simple_plotter_qt-0.1.0.dist-info/RECORD
