Metadata-Version: 2.1
Name: simple-plotter-qt
Version: 0.1.0
Summary: Qt-based GUI front-end for simple-plotter
Home-page: https://simple-plotter.readthedocs.io/en/latest/
Author: Thies Hecker
Author-email: thies.hecker@gmx.de
License: GPL3
Project-URL: Documentation, https://simple-plotter.readthedocs.io/
Project-URL: Source Code, https://gitlab.com/thecker/simple-plotter-qt/
Keywords: plot plotting matplotlib gui
Platform: UNKNOWN
Classifier: License :: OSI Approved :: GNU General Public License v3 (GPLv3)
Requires-Python: >=3
Requires-Dist: simple-plotter
Requires-Dist: setuptools-scm
Requires-Dist: matplotlib (>=2)
Requires-Dist: PyQt5
